{
  "ComponentIndexes": {},
  "ControlUniqueGuids": {},
  "ControlUniqueIds": {
    "Acessivel": 271,
    "AddArquivo": 34,
    "AddMediaButton1": 35,
    "AddPicture1": 184,
    "ajuda": 28,
    "Ajuda": 300,
    "Ajuda_1": 30,
    "Anexo_DataCard1": 180,
    "Anexos_DataCard1": 175,
    "Anexos_DataCard2": 234,
    "App": 1,
    "Argentina": 288,
    "Aumentar fonte": 292,
    "Body3": 261,
    "Body3_1": 21,
    "Brasil": 287,
    "Button2": 44,
    "color_amarelo": 277,
    "color_branco": 278,
    "color_preto": 279,
    "Configuracao": 299,
    "Container1": 6,
    "Container1_1": 245,
    "Data_DataCard1": 125,
    "Data_DataCard2": 48,
    "DataCardKey1": 162,
    "DataCardKey10": 122,
    "DataCardKey11": 55,
    "DataCardKey12": 147,
    "DataCardKey13": 117,
    "DataCardKey14": 177,
    "DataCardKey15": 152,
    "DataCardKey16": 167,
    "DataCardKey17": 157,
    "DataCardKey18": 142,
    "DataCardKey19": 132,
    "DataCardKey2": 127,
    "DataCardKey21": 50,
    "DataCardKey22": 196,
    "DataCardKey23": 211,
    "DataCardKey24": 216,
    "DataCardKey25": 221,
    "DataCardKey26": 226,
    "DataCardKey27": 206,
    "DataCardKey28": 201,
    "DataCardKey29": 70,
    "DataCardKey3": 110,
    "DataCardKey30": 75,
    "DataCardKey31": 80,
    "DataCardKey32": 85,
    "DataCardKey33": 231,
    "DataCardKey34": 90,
    "DataCardKey35": 95,
    "DataCardKey36": 100,
    "DataCardKey37": 105,
    "DataCardKey38": 236,
    "DataCardKey4": 182,
    "DataCardKey6": 60,
    "DataCardKey7": 137,
    "DataCardKey8": 65,
    "DataCardKey9": 172,
    "DataCardValue1": 163,
    "DataCardValue10": 148,
    "DataCardValue11": 118,
    "DataCardValue12": 56,
    "DataCardValue13": 153,
    "DataCardValue14": 168,
    "DataCardValue15": 158,
    "DataCardValue16": 143,
    "DataCardValue17": 133,
    "DataCardValue18": 178,
    "DataCardValue19": 232,
    "DataCardValue2": 128,
    "DataCardValue20": 197,
    "DataCardValue21": 212,
    "DataCardValue22": 217,
    "DataCardValue23": 222,
    "DataCardValue24": 227,
    "DataCardValue25": 207,
    "DataCardValue26": 202,
    "DataCardValue27": 237,
    "DataCardValue28": 51,
    "DataCardValue29": 71,
    "DataCardValue3": 111,
    "DataCardValue30": 76,
    "DataCardValue31": 81,
    "DataCardValue32": 86,
    "DataCardValue34": 91,
    "DataCardValue35": 96,
    "DataCardValue36": 101,
    "DataCardValue37": 106,
    "DataCardValue5": 61,
    "DataCardValue6": 138,
    "DataCardValue7": 66,
    "DataCardValue8": 173,
    "DataCardValue9": 123,
    "ErrorMessage1": 164,
    "ErrorMessage10": 124,
    "ErrorMessage11": 228,
    "ErrorMessage12": 149,
    "ErrorMessage13": 119,
    "ErrorMessage14": 208,
    "ErrorMessage15": 154,
    "ErrorMessage16": 169,
    "ErrorMessage17": 159,
    "ErrorMessage18": 144,
    "ErrorMessage19": 134,
    "ErrorMessage2": 129,
    "ErrorMessage20": 62,
    "ErrorMessage21": 203,
    "ErrorMessage22": 139,
    "ErrorMessage23": 67,
    "ErrorMessage24": 174,
    "ErrorMessage25": 57,
    "ErrorMessage26": 52,
    "ErrorMessage27": 72,
    "ErrorMessage28": 77,
    "ErrorMessage29": 82,
    "ErrorMessage3": 112,
    "ErrorMessage30": 87,
    "ErrorMessage31": 92,
    "ErrorMessage32": 97,
    "ErrorMessage33": 102,
    "ErrorMessage34": 107,
    "ErrorMessage35": 179,
    "ErrorMessage37": 233,
    "ErrorMessage38": 238,
    "ErrorMessage4": 185,
    "ErrorMessage6": 198,
    "ErrorMessage7": 213,
    "ErrorMessage8": 218,
    "ErrorMessage9": 223,
    "Fabricante_DataCard1": 108,
    "Fabricante_DataCard2": 150,
    "Fabricante_DataCard3": 214,
    "Fechar": 289,
    "Filtro": 10,
    "Filtro_1": 249,
    "Fontes": 280,
    "Fontes_3": 282,
    "Fontes_4": 285,
    "Form1": 114,
    "Form2": 193,
    "Form5": 47,
    "Gallery2": 255,
    "Gallery2_1": 16,
    "galleryTemplate3": 256,
    "galleryTemplate3_1": 17,
    "Group1": 39,
    "Group10": 268,
    "Group11": 269,
    "Group11_1": 191,
    "Group12": 267,
    "Group2": 291,
    "Group4": 27,
    "Group4_1": 242,
    "Group5": 303,
    "Group7": 26,
    "Group8": 190,
    "Host": 3,
    "Icon1": 189,
    "Icon2": 257,
    "Icon3": 13,
    "Icon3_1": 15,
    "Icon3_2": 252,
    "Icon3_3": 254,
    "Icon4": 265,
    "Icon5": 293,
    "Icon5_1": 301,
    "Icon6": 14,
    "Icon6_1": 253,
    "Icon7": 266,
    "Icon7_2": 25,
    "Icon7_4": 37,
    "Icon7_5": 188,
    "Icon7_6": 240,
    "Image3": 183,
    "Image5": 41,
    "Imagem do material": 246,
    "Imagem do material 2": 7,
    "Label1": 294,
    "Label2_2": 113,
    "Label3": 264,
    "Label3_2": 186,
    "Label3_3": 24,
    "Label3_5": 263,
    "Label3_6": 38,
    "Label3_7": 187,
    "Label3_8": 239,
    "Label4": 284,
    "Label4_1": 281,
    "Localização_DataCard1": 130,
    "Localização_DataCard2": 199,
    "Localização_DataCard4": 68,
    "localizar": 4,
    "Localizar 2": 192,
    "Localizar Button": 297,
    "login": 40,
    "Logo estoque": 296,
    "Logo Estoque": 244,
    "Logo estoque_1": 32,
    "Logo Estoque_1": 5,
    "MABEC_DataCard2": 165,
    "MABEC_DataCard3": 219,
    "MABEC_DataCard4": 73,
    "Material_DataCard1": 78,
    "Material_DataCard2": 115,
    "Material_DataCard3": 194,
    "Modelo Material_DataCard2": 155,
    "Modelo Material_DataCard3": 224,
    "Modelo Material_DataCard4": 83,
    "movimentacao": 243,
    "Movimentacao Button": 298,
    "Movimentacao Button_1": 241,
    "movimentacao2": 46,
    "NextArrow5": 258,
    "NextArrow5_1": 18,
    "Nome (field_2)_DataCard2": 145,
    "Nome_DataCard5": 98,
    "Nota Fiscal_DataCard1": 170,
    "Nota Fiscal_DataCard2": 53,
    "PopUp_acessibilidade": 272,
    "principal": 270,
    "Projeto_DataCard1": 229,
    "Projeto_DataCard2": 58,
    "Projeto_DataCard3": 135,
    "Projeto_DataCard4": 63,
    "Quant._DataCard1": 204,
    "Quant._DataCard2": 140,
    "Quant._DataCard4": 88,
    "Radio1": 11,
    "Radio1_1": 250,
    "Radio1_2": 251,
    "Radio1_3": 12,
    "Referência_DataCard1": 160,
    "Referência_DataCard2": 209,
    "Referência_DataCard4": 93,
    "Separator5_1": 22,
    "Separator5_2": 262,
    "Slider1": 283,
    "StarVisible1": 161,
    "StarVisible10": 121,
    "StarVisible11": 225,
    "StarVisible12": 146,
    "StarVisible13": 116,
    "StarVisible14": 205,
    "StarVisible15": 151,
    "StarVisible16": 166,
    "StarVisible17": 156,
    "StarVisible18": 141,
    "StarVisible19": 131,
    "StarVisible2": 126,
    "StarVisible20": 59,
    "StarVisible21": 200,
    "StarVisible22": 136,
    "StarVisible23": 64,
    "StarVisible24": 171,
    "StarVisible25": 54,
    "StarVisible26": 49,
    "StarVisible27": 69,
    "StarVisible28": 74,
    "StarVisible29": 79,
    "StarVisible3": 109,
    "StarVisible30": 84,
    "StarVisible31": 89,
    "StarVisible32": 94,
    "StarVisible33": 99,
    "StarVisible34": 104,
    "StarVisible35": 176,
    "StarVisible37": 230,
    "StarVisible38": 235,
    "StarVisible4": 181,
    "StarVisible6": 195,
    "StarVisible7": 210,
    "StarVisible8": 215,
    "StarVisible9": 220,
    "Status_DataCard1": 103,
    "Status_DataCard2": 120,
    "Subtitle5": 260,
    "Subtitle5_1": 20,
    "tema": 273,
    "tema claro": 275,
    "tema daltonico": 274,
    "tema escuro": 276,
    "tema_1": 286,
    "Temas": 290,
    "TextInput1": 43,
    "TextInput2": 42,
    "TextInput3": 33,
    "TextInput3_1": 29,
    "TextSearchBox1_1": 248,
    "TextSearchBox1_2": 9,
    "Timer1": 247,
    "Timer1_1": 8,
    "Timer2": 295,
    "Title5": 259,
    "Title5_1": 19,
    "Tooling Logo": 302,
    "Tooling Logo_1": 45,
    "Tooling Logo_2": 23,
    "Tooling Logo_4": 36,
    "UploadedImage1": 31
  },
  "FunctionParamsInvariantScripts": {},
  "FunctionParamsInvariantScriptsOnInstances": {},
  "HeaderLastSavedDateTimeUTC": "04/18/2024 14:29:49",
  "IsLegacyComponentAllowGlobalScopeCase": false,
  "LocalConnectionIDReferences": {
    "225faf01-38b7-4ed7-90b0-e781b44771a2": "\"/providers/microsoft.powerapps/apis/shared_sharepointonline/connections/998b214cac5743a1ac8fd7a960171a38\"",
    "a04bc8d5-7d32-429a-80e1-2e2d32cf0e14": "\"/providers/microsoft.powerapps/apis/shared_office365/connections/fe29ff7ed03344fdba6700dd1e27b745\"",
    "b554229c-d2e6-4b42-8782-235c738de200": "\"/providers/microsoft.powerapps/apis/shared_sharepointonline/connections/1bb9748304ba489e84ad3970a53a3afa\""
  },
  "LocalDatabaseReferencesAsEmpty": true,
  "LocalResourceFileNames": {
    "1": "ea5b107d-e79b-4774-b11c-e9fbcd474daa.png",
    "186203": "364242ec-3e6a-4d8e-8e92-c665495dc7e8.png",
    "197376": "9b830714-eaef-43b9-94bd-dcd2dce4fef2.png",
    "197573": "b827a649-85b9-4f6c-b509-652d93c95203.png",
    "2": "1f124b38-4a78-4051-a34c-5c97a08c1c25.png",
    "2_1": "ceb6d177-a8d9-44a3-a863-e8d96f522aff.png",
    "Design sem nome": "33c1c14c-4fb4-4cc1-b125-a9ad182a7eef.png",
    "Design sem nome (1)": "ad410fa3-5ffa-4dcc-8fbf-6f86f67aeb70.png",
    "Design sem nome (2)": "c5929a66-5e6c-45b5-a6b6-e54569f0f690.png",
    "Imagem não encontrada": "c433c6f9-b56a-40b8-9c0a-deb728ada080.png",
    "Logo Tooling - vetor": "86aaaf9b-25d2-4055-b711-07d36d9d85bd.svg",
    "MicrosoftTeams-image (2)": "ddd5d6b9-82a3-42ad-a414-01231ab0c205.png",
    "MicrosoftTeams-image (5)": "b39ff723-a06d-497f-844d-57cc8c04feb5.png",
    "MicrosoftTeams-image (6)": "ce70a4ac-8c76-4ea7-84c1-b538a46e0fe3.png"
  },
  "LocalResourceRootPaths": {
    "1": "https://docserverpwaprodweu.blob.core.windows.net/52830893-5e45-4aa8-b99c-7c846cbe9970-1/resource/Assets0Images0ea5b107d-e79b-4774-b11c-e9fbcd474daa.png?skoid=58690ece-ec83-4ce2-9ce8-883d4d6a54ee&sktid=975f013f-7f24-47e8-a7d3-abc4752bf346&skt=2024-04-18T14%3A27%3A15Z&ske=2024-04-19T14%3A42%3A15Z&sks=b&skv=2022-11-02&sv=2022-11-02&spr=https&se=2024-04-19T14%3A42%3A15Z&sr=b&sp=r&sig=xMawxRHZLUjd9l9DV6%2FgjM1zgqUJTcxRxUHaVkIfF0Q%3D",
    "186203": "https://docserverpwaprodweu.blob.core.windows.net/52830893-5e45-4aa8-b99c-7c846cbe9970-1/resource/Assets0Images0364242ec-3e6a-4d8e-8e92-c665495dc7e8.png?skoid=58690ece-ec83-4ce2-9ce8-883d4d6a54ee&sktid=975f013f-7f24-47e8-a7d3-abc4752bf346&skt=2024-04-18T14%3A27%3A15Z&ske=2024-04-19T14%3A42%3A15Z&sks=b&skv=2022-11-02&sv=2022-11-02&spr=https&se=2024-04-19T14%3A42%3A15Z&sr=b&sp=r&sig=aG3Wffb0Dq67UPGvNjxYTgDck4by0Z3hFPG9Lds1oLM%3D",
    "197376": "https://docserverpwaprodweu.blob.core.windows.net/52830893-5e45-4aa8-b99c-7c846cbe9970-1/resource/Assets0Images09b830714-eaef-43b9-94bd-dcd2dce4fef2.png?skoid=58690ece-ec83-4ce2-9ce8-883d4d6a54ee&sktid=975f013f-7f24-47e8-a7d3-abc4752bf346&skt=2024-04-18T14%3A27%3A15Z&ske=2024-04-19T14%3A42%3A15Z&sks=b&skv=2022-11-02&sv=2022-11-02&spr=https&se=2024-04-19T14%3A42%3A15Z&sr=b&sp=r&sig=TXVl014M8HL9%2BT69YvD1vAhZcJTsguq3mjBRJ2knXVU%3D",
    "197573": "https://docserverpwaprodweu.blob.core.windows.net/52830893-5e45-4aa8-b99c-7c846cbe9970-1/resource/Assets0Images0b827a649-85b9-4f6c-b509-652d93c95203.png?skoid=58690ece-ec83-4ce2-9ce8-883d4d6a54ee&sktid=975f013f-7f24-47e8-a7d3-abc4752bf346&skt=2024-04-18T14%3A27%3A15Z&ske=2024-04-19T14%3A42%3A15Z&sks=b&skv=2022-11-02&sv=2022-11-02&spr=https&se=2024-04-19T14%3A42%3A15Z&sr=b&sp=r&sig=9Tub26QWvq3yDsnbCx769F7LODmho%2Bcdsqwv5Xz%2B2%2Fs%3D",
    "2": "https://docserverpwaprodweu.blob.core.windows.net/52830893-5e45-4aa8-b99c-7c846cbe9970-1/resource/Assets0Images01f124b38-4a78-4051-a34c-5c97a08c1c25.png?skoid=58690ece-ec83-4ce2-9ce8-883d4d6a54ee&sktid=975f013f-7f24-47e8-a7d3-abc4752bf346&skt=2024-04-18T14%3A27%3A15Z&ske=2024-04-19T14%3A42%3A15Z&sks=b&skv=2022-11-02&sv=2022-11-02&spr=https&se=2024-04-19T14%3A42%3A15Z&sr=b&sp=r&sig=ZJBcXxTTFpnyZVq4nP70WYhwzAM27emxKEviUiSsPoM%3D",
    "2_1": "https://docserverpwaprodweu.blob.core.windows.net/52830893-5e45-4aa8-b99c-7c846cbe9970-1/resource/Assets0Images0ceb6d177-a8d9-44a3-a863-e8d96f522aff.png?skoid=58690ece-ec83-4ce2-9ce8-883d4d6a54ee&sktid=975f013f-7f24-47e8-a7d3-abc4752bf346&skt=2024-04-18T14%3A27%3A15Z&ske=2024-04-19T14%3A42%3A15Z&sks=b&skv=2022-11-02&sv=2022-11-02&spr=https&se=2024-04-19T14%3A42%3A15Z&sr=b&sp=r&sig=t5MNK8po38Dqzr8YybvYYBWCc86hmTkE7CxO8M4OTW0%3D",
    "Design sem nome": "https://docserverpwaprodweu.blob.core.windows.net/52830893-5e45-4aa8-b99c-7c846cbe9970-1/resource/Assets0Images033c1c14c-4fb4-4cc1-b125-a9ad182a7eef.png?skoid=58690ece-ec83-4ce2-9ce8-883d4d6a54ee&sktid=975f013f-7f24-47e8-a7d3-abc4752bf346&skt=2024-04-18T14%3A27%3A15Z&ske=2024-04-19T14%3A42%3A15Z&sks=b&skv=2022-11-02&sv=2022-11-02&spr=https&se=2024-04-19T14%3A42%3A15Z&sr=b&sp=r&sig=kevi7495ynHnDuoO%2F69CCS761L7VOcaysvYwxgce3HI%3D",
    "Design sem nome (1)": "https://docserverpwaprodweu.blob.core.windows.net/52830893-5e45-4aa8-b99c-7c846cbe9970-1/resource/Assets0Images0ad410fa3-5ffa-4dcc-8fbf-6f86f67aeb70.png?skoid=58690ece-ec83-4ce2-9ce8-883d4d6a54ee&sktid=975f013f-7f24-47e8-a7d3-abc4752bf346&skt=2024-04-18T14%3A27%3A15Z&ske=2024-04-19T14%3A42%3A15Z&sks=b&skv=2022-11-02&sv=2022-11-02&spr=https&se=2024-04-19T14%3A42%3A15Z&sr=b&sp=r&sig=vKwtKpk0qPjBg9cyZ5n50pyNenWxWKFCAL0BmvYJP4E%3D",
    "Design sem nome (2)": "https://docserverpwaprodweu.blob.core.windows.net/52830893-5e45-4aa8-b99c-7c846cbe9970-1/resource/Assets0Images0c5929a66-5e6c-45b5-a6b6-e54569f0f690.png?skoid=58690ece-ec83-4ce2-9ce8-883d4d6a54ee&sktid=975f013f-7f24-47e8-a7d3-abc4752bf346&skt=2024-04-18T14%3A27%3A15Z&ske=2024-04-19T14%3A42%3A15Z&sks=b&skv=2022-11-02&sv=2022-11-02&spr=https&se=2024-04-19T14%3A42%3A15Z&sr=b&sp=r&sig=N4Gesc9vBDkbp%2FbetxrYmZB%2FHZupFVg%2Fc%2FjqYQ9sP2s%3D",
    "Imagem não encontrada": "https://docserverpwaprodweu.blob.core.windows.net/52830893-5e45-4aa8-b99c-7c846cbe9970-1/resource/Assets0Images0c433c6f9-b56a-40b8-9c0a-deb728ada080.png?skoid=58690ece-ec83-4ce2-9ce8-883d4d6a54ee&sktid=975f013f-7f24-47e8-a7d3-abc4752bf346&skt=2024-04-18T14%3A27%3A14Z&ske=2024-04-19T14%3A42%3A14Z&sks=b&skv=2022-11-02&sv=2022-11-02&spr=https&se=2024-04-19T14%3A42%3A14Z&sr=b&sp=r&sig=uxcToCDEWPP4iMeTX%2FGZFSintzMnn2Nu%2Fqt0v0GNYu0%3D",
    "Logo Tooling - vetor": "https://docserverpwaprodweu.blob.core.windows.net/52830893-5e45-4aa8-b99c-7c846cbe9970-1/resource/Assets0Images086aaaf9b-25d2-4055-b711-07d36d9d85bd.svg?skoid=58690ece-ec83-4ce2-9ce8-883d4d6a54ee&sktid=975f013f-7f24-47e8-a7d3-abc4752bf346&skt=2024-04-18T14%3A27%3A14Z&ske=2024-04-19T14%3A42%3A14Z&sks=b&skv=2022-11-02&sv=2022-11-02&spr=https&se=2024-04-19T14%3A42%3A14Z&sr=b&sp=r&sig=vjLhRvK4G%2FHzEuZcWMJt6vflTx3fvJisLg59pKsxRU8%3D",
    "MicrosoftTeams-image (2)": "https://docserverpwaprodweu.blob.core.windows.net/52830893-5e45-4aa8-b99c-7c846cbe9970-1/resource/Assets0Images0ddd5d6b9-82a3-42ad-a414-01231ab0c205.png?skoid=58690ece-ec83-4ce2-9ce8-883d4d6a54ee&sktid=975f013f-7f24-47e8-a7d3-abc4752bf346&skt=2024-04-18T14%3A27%3A14Z&ske=2024-04-19T14%3A42%3A14Z&sks=b&skv=2022-11-02&sv=2022-11-02&spr=https&se=2024-04-19T14%3A42%3A14Z&sr=b&sp=r&sig=eK5ZadgrPrrP5ajjp4avp6jbZP9PNHew8QEYVQFeZ2U%3D",
    "MicrosoftTeams-image (5)": "https://docserverpwaprodweu.blob.core.windows.net/52830893-5e45-4aa8-b99c-7c846cbe9970-1/resource/Assets0Images0b39ff723-a06d-497f-844d-57cc8c04feb5.png?skoid=58690ece-ec83-4ce2-9ce8-883d4d6a54ee&sktid=975f013f-7f24-47e8-a7d3-abc4752bf346&skt=2024-04-18T14%3A27%3A14Z&ske=2024-04-19T14%3A42%3A14Z&sks=b&skv=2022-11-02&sv=2022-11-02&spr=https&se=2024-04-19T14%3A42%3A14Z&sr=b&sp=r&sig=caipQ5TWU65Kw3t46yuAYDy1pdQgeuxeNT2rjWtxc%2FI%3D",
    "MicrosoftTeams-image (6)": "https://docserverpwaprodweu.blob.core.windows.net/52830893-5e45-4aa8-b99c-7c846cbe9970-1/resource/Assets0Images0ce70a4ac-8c76-4ea7-84c1-b538a46e0fe3.png?skoid=58690ece-ec83-4ce2-9ce8-883d4d6a54ee&sktid=975f013f-7f24-47e8-a7d3-abc4752bf346&skt=2024-04-18T14%3A27%3A14Z&ske=2024-04-19T14%3A42%3A14Z&sks=b&skv=2022-11-02&sv=2022-11-02&spr=https&se=2024-04-19T14%3A42%3A14Z&sr=b&sp=r&sig=ozMaLnpBnZH9zyWcQur1C3Cn3DBpFGxCh8KQ9vlEKo4%3D"
  },
  "OldLogoFileName": "yhtiwtxg.jpg",
  "OrderComponentMetadata": {},
  "OrderComponentTemplate": {},
  "OrderDataSource": {
    "ComboBoxSample": 3,
    "CONTROLEDEMATERIAIS": 4,
    "CustomGallerySample": 1,
    "DropDownSample": 2,
    "ESTOQUEPROJETOS": 6,
    "Office365Outlook": 0,
    "RadioSample": 5
  },
  "OrderGroupControls": {
    "Aumentar fonte": {
      "Fontes_3": 1,
      "Slider1": 0
    },
    "Group1": {
      "AddArquivo": 3,
      "AddMediaButton1": 2,
      "TextInput3": 0,
      "TextInput3_1": 1
    },
    "Group10": {
      "Icon4": 1,
      "Label3_5": 0
    },
    "Group11": {
      "Icon7": 1,
      "Label3": 0
    },
    "Group11_1": {
      "Icon7_5": 1,
      "Label3_7": 0
    },
    "Group12": {
      "Filtro_1": 2,
      "Gallery2": 5,
      "Icon3_2": 1,
      "Icon3_3": 3,
      "Icon6_1": 0,
      "TextSearchBox1_1": 4
    },
    "Group2": {
      "Label4": 1,
      "Label4_1": 0
    },
    "Group4": {
      "Icon7_2": 1,
      "Label3_3": 0
    },
    "Group4_1": {
      "Icon7_6": 1,
      "Label3_8": 0
    },
    "Group5": {
      "Icon5": 0,
      "Timer2": 1
    },
    "Group7": {
      "Filtro": 4,
      "Gallery2_1": 2,
      "Icon3": 5,
      "Icon3_1": 1,
      "Icon6": 0,
      "TextSearchBox1_2": 3
    },
    "Group8": {
      "Icon1": 1,
      "Label3_2": 0
    },
    "Temas": {
      "tema": 0,
      "tema claro": 2,
      "tema daltonico": 3,
      "tema escuro": 1
    }
  },
  "OrderPcfTemplate": {},
  "OrderTemplate": {},
  "OrderXMLTemplate": {
    "addMedia": 10,
    "attachments": 14,
    "button": 9,
    "combobox": 13,
    "datepicker": 12,
    "form": 11,
    "gallery": 6,
    "groupContainer": 1,
    "icon": 5,
    "image": 0,
    "label": 7,
    "radio": 4,
    "rectangle": 8,
    "slider": 15,
    "text": 3,
    "timer": 2
  },
  "OverridablePropertiesEntry": {
    "Acessivel": {},
    "AddArquivo": {},
    "AddMediaButton1": {},
    "AddPicture1": {},
    "ajuda": {},
    "Ajuda": {},
    "Ajuda_1": {},
    "Anexo_DataCard1": {},
    "Anexos_DataCard1": {},
    "Anexos_DataCard2": {},
    "App": {},
    "Argentina": {},
    "Aumentar fonte": {},
    "Body3": {},
    "Body3_1": {},
    "Brasil": {},
    "Button2": {},
    "color_amarelo": {},
    "color_branco": {},
    "color_preto": {},
    "Configuracao": {},
    "Container1": {},
    "Container1_1": {},
    "Data_DataCard1": {},
    "Data_DataCard2": {},
    "DataCardKey1": {},
    "DataCardKey10": {},
    "DataCardKey11": {},
    "DataCardKey12": {},
    "DataCardKey13": {},
    "DataCardKey14": {},
    "DataCardKey15": {},
    "DataCardKey16": {},
    "DataCardKey17": {},
    "DataCardKey18": {},
    "DataCardKey19": {},
    "DataCardKey2": {},
    "DataCardKey21": {},
    "DataCardKey22": {},
    "DataCardKey23": {},
    "DataCardKey24": {},
    "DataCardKey25": {},
    "DataCardKey26": {},
    "DataCardKey27": {},
    "DataCardKey28": {},
    "DataCardKey29": {},
    "DataCardKey3": {},
    "DataCardKey30": {},
    "DataCardKey31": {},
    "DataCardKey32": {},
    "DataCardKey33": {},
    "DataCardKey34": {},
    "DataCardKey35": {},
    "DataCardKey36": {},
    "DataCardKey37": {},
    "DataCardKey38": {},
    "DataCardKey4": {},
    "DataCardKey6": {},
    "DataCardKey7": {},
    "DataCardKey8": {},
    "DataCardKey9": {},
    "DataCardValue1": {},
    "DataCardValue10": {},
    "DataCardValue11": {},
    "DataCardValue12": {},
    "DataCardValue13": {},
    "DataCardValue14": {},
    "DataCardValue15": {},
    "DataCardValue16": {},
    "DataCardValue17": {},
    "DataCardValue18": {},
    "DataCardValue19": {},
    "DataCardValue2": {},
    "DataCardValue20": {},
    "DataCardValue21": {},
    "DataCardValue22": {},
    "DataCardValue23": {},
    "DataCardValue24": {},
    "DataCardValue25": {},
    "DataCardValue26": {},
    "DataCardValue27": {},
    "DataCardValue28": {},
    "DataCardValue29": {},
    "DataCardValue3": {},
    "DataCardValue30": {},
    "DataCardValue31": {},
    "DataCardValue32": {},
    "DataCardValue34": {},
    "DataCardValue35": {},
    "DataCardValue36": {},
    "DataCardValue37": {},
    "DataCardValue5": {},
    "DataCardValue6": {},
    "DataCardValue7": {},
    "DataCardValue8": {},
    "DataCardValue9": {},
    "ErrorMessage1": {},
    "ErrorMessage10": {},
    "ErrorMessage11": {},
    "ErrorMessage12": {},
    "ErrorMessage13": {},
    "ErrorMessage14": {},
    "ErrorMessage15": {},
    "ErrorMessage16": {},
    "ErrorMessage17": {},
    "ErrorMessage18": {},
    "ErrorMessage19": {},
    "ErrorMessage2": {},
    "ErrorMessage20": {},
    "ErrorMessage21": {},
    "ErrorMessage22": {},
    "ErrorMessage23": {},
    "ErrorMessage24": {},
    "ErrorMessage25": {},
    "ErrorMessage26": {},
    "ErrorMessage27": {},
    "ErrorMessage28": {},
    "ErrorMessage29": {},
    "ErrorMessage3": {},
    "ErrorMessage30": {},
    "ErrorMessage31": {},
    "ErrorMessage32": {},
    "ErrorMessage33": {},
    "ErrorMessage34": {},
    "ErrorMessage35": {},
    "ErrorMessage37": {},
    "ErrorMessage38": {},
    "ErrorMessage4": {},
    "ErrorMessage6": {},
    "ErrorMessage7": {},
    "ErrorMessage8": {},
    "ErrorMessage9": {},
    "Fabricante_DataCard1": {},
    "Fabricante_DataCard2": {},
    "Fabricante_DataCard3": {},
    "Fechar": {},
    "Filtro": {},
    "Filtro_1": {},
    "Fontes": {},
    "Fontes_3": {},
    "Fontes_4": {},
    "Form1": {},
    "Form2": {},
    "Form5": {},
    "Gallery2": {},
    "Gallery2_1": {},
    "galleryTemplate3": {},
    "galleryTemplate3_1": {},
    "Group1": {},
    "Group10": {},
    "Group11": {},
    "Group11_1": {},
    "Group12": {},
    "Group2": {},
    "Group4": {},
    "Group4_1": {},
    "Group5": {},
    "Group7": {},
    "Group8": {},
    "Host": {},
    "Icon1": {},
    "Icon2": {},
    "Icon3": {},
    "Icon3_1": {},
    "Icon3_2": {},
    "Icon3_3": {},
    "Icon4": {},
    "Icon5": {},
    "Icon5_1": {},
    "Icon6": {},
    "Icon6_1": {},
    "Icon7": {},
    "Icon7_2": {},
    "Icon7_4": {},
    "Icon7_5": {},
    "Icon7_6": {},
    "Image3": {},
    "Image5": {},
    "Imagem do material": {},
    "Imagem do material 2": {},
    "Label1": {},
    "Label2_2": {},
    "Label3": {},
    "Label3_2": {},
    "Label3_3": {},
    "Label3_5": {},
    "Label3_6": {},
    "Label3_7": {},
    "Label3_8": {},
    "Label4": {},
    "Label4_1": {},
    "Localização_DataCard1": {},
    "Localização_DataCard2": {},
    "Localização_DataCard4": {},
    "localizar": {},
    "Localizar 2": {},
    "Localizar Button": {},
    "login": {},
    "Logo estoque": {},
    "Logo Estoque": {},
    "Logo estoque_1": {},
    "Logo Estoque_1": {},
    "MABEC_DataCard2": {},
    "MABEC_DataCard3": {},
    "MABEC_DataCard4": {},
    "Material_DataCard1": {},
    "Material_DataCard2": {},
    "Material_DataCard3": {},
    "Modelo Material_DataCard2": {},
    "Modelo Material_DataCard3": {},
    "Modelo Material_DataCard4": {},
    "movimentacao": {},
    "Movimentacao Button": {},
    "Movimentacao Button_1": {},
    "movimentacao2": {},
    "NextArrow5": {},
    "NextArrow5_1": {},
    "Nome (field_2)_DataCard2": {},
    "Nome_DataCard5": {},
    "Nota Fiscal_DataCard1": {},
    "Nota Fiscal_DataCard2": {},
    "PopUp_acessibilidade": {},
    "principal": {},
    "Projeto_DataCard1": {},
    "Projeto_DataCard2": {},
    "Projeto_DataCard3": {},
    "Projeto_DataCard4": {},
    "Quant._DataCard1": {},
    "Quant._DataCard2": {},
    "Quant._DataCard4": {},
    "Radio1": {},
    "Radio1_1": {},
    "Radio1_2": {},
    "Radio1_3": {},
    "Referência_DataCard1": {},
    "Referência_DataCard2": {},
    "Referência_DataCard4": {},
    "Separator5_1": {},
    "Separator5_2": {},
    "Slider1": {},
    "StarVisible1": {},
    "StarVisible10": {},
    "StarVisible11": {},
    "StarVisible12": {},
    "StarVisible13": {},
    "StarVisible14": {},
    "StarVisible15": {},
    "StarVisible16": {},
    "StarVisible17": {},
    "StarVisible18": {},
    "StarVisible19": {},
    "StarVisible2": {},
    "StarVisible20": {},
    "StarVisible21": {},
    "StarVisible22": {},
    "StarVisible23": {},
    "StarVisible24": {},
    "StarVisible25": {},
    "StarVisible26": {},
    "StarVisible27": {},
    "StarVisible28": {},
    "StarVisible29": {},
    "StarVisible3": {},
    "StarVisible30": {},
    "StarVisible31": {},
    "StarVisible32": {},
    "StarVisible33": {},
    "StarVisible34": {},
    "StarVisible35": {},
    "StarVisible37": {},
    "StarVisible38": {},
    "StarVisible4": {},
    "StarVisible6": {},
    "StarVisible7": {},
    "StarVisible8": {},
    "StarVisible9": {},
    "Status_DataCard1": {},
    "Status_DataCard2": {},
    "Subtitle5": {},
    "Subtitle5_1": {},
    "tema": {},
    "tema claro": {},
    "tema daltonico": {},
    "tema escuro": {},
    "tema_1": {},
    "Temas": {},
    "TextInput1": {},
    "TextInput2": {},
    "TextInput3": {},
    "TextInput3_1": {},
    "TextSearchBox1_1": {},
    "TextSearchBox1_2": {},
    "Timer1": {},
    "Timer1_1": {},
    "Timer2": {},
    "Title5": {},
    "Title5_1": {},
    "Tooling Logo": {},
    "Tooling Logo_1": {},
    "Tooling Logo_2": {},
    "Tooling Logo_4": {},
    "UploadedImage1": {}
  },
  "PCFDynamicSchemaForIRRetrievalEntry": {},
  "PCFTemplateEntry": {},
  "PublishOrderIndices": {
    "Acessivel": 5,
    "AddArquivo": 44,
    "AddMediaButton1": 45,
    "AddPicture1": 285,
    "ajuda": 0,
    "Ajuda": 35,
    "Ajuda_1": 39,
    "Anexo_DataCard1": 281,
    "Anexos_DataCard1": 276,
    "Anexos_DataCard2": 113,
    "App": 0,
    "Argentina": 25,
    "Aumentar fonte": 19,
    "Body3": 140,
    "Body3_1": 66,
    "Brasil": 24,
    "Button2": 3,
    "color_amarelo": 12,
    "color_branco": 13,
    "color_preto": 14,
    "Configuracao": 34,
    "Container1": 50,
    "Container1_1": 123,
    "Data_DataCard1": 226,
    "Data_DataCard2": 149,
    "DataCardKey1": 263,
    "DataCardKey10": 223,
    "DataCardKey11": 156,
    "DataCardKey12": 248,
    "DataCardKey13": 218,
    "DataCardKey14": 278,
    "DataCardKey15": 253,
    "DataCardKey16": 268,
    "DataCardKey17": 258,
    "DataCardKey18": 243,
    "DataCardKey19": 233,
    "DataCardKey2": 228,
    "DataCardKey21": 151,
    "DataCardKey22": 75,
    "DataCardKey23": 90,
    "DataCardKey24": 95,
    "DataCardKey25": 100,
    "DataCardKey26": 105,
    "DataCardKey27": 85,
    "DataCardKey28": 80,
    "DataCardKey29": 171,
    "DataCardKey3": 211,
    "DataCardKey30": 176,
    "DataCardKey31": 181,
    "DataCardKey32": 186,
    "DataCardKey33": 110,
    "DataCardKey34": 191,
    "DataCardKey35": 196,
    "DataCardKey36": 201,
    "DataCardKey37": 206,
    "DataCardKey38": 115,
    "DataCardKey4": 283,
    "DataCardKey6": 161,
    "DataCardKey7": 238,
    "DataCardKey8": 166,
    "DataCardKey9": 273,
    "DataCardValue1": 264,
    "DataCardValue10": 249,
    "DataCardValue11": 219,
    "DataCardValue12": 157,
    "DataCardValue13": 254,
    "DataCardValue14": 269,
    "DataCardValue15": 259,
    "DataCardValue16": 244,
    "DataCardValue17": 234,
    "DataCardValue18": 279,
    "DataCardValue19": 111,
    "DataCardValue2": 229,
    "DataCardValue20": 76,
    "DataCardValue21": 91,
    "DataCardValue22": 96,
    "DataCardValue23": 101,
    "DataCardValue24": 106,
    "DataCardValue25": 86,
    "DataCardValue26": 81,
    "DataCardValue27": 116,
    "DataCardValue28": 152,
    "DataCardValue29": 172,
    "DataCardValue3": 212,
    "DataCardValue30": 177,
    "DataCardValue31": 182,
    "DataCardValue32": 187,
    "DataCardValue34": 192,
    "DataCardValue35": 197,
    "DataCardValue36": 202,
    "DataCardValue37": 207,
    "DataCardValue5": 162,
    "DataCardValue6": 239,
    "DataCardValue7": 167,
    "DataCardValue8": 274,
    "DataCardValue9": 224,
    "ErrorMessage1": 265,
    "ErrorMessage10": 225,
    "ErrorMessage11": 107,
    "ErrorMessage12": 250,
    "ErrorMessage13": 220,
    "ErrorMessage14": 87,
    "ErrorMessage15": 255,
    "ErrorMessage16": 270,
    "ErrorMessage17": 260,
    "ErrorMessage18": 245,
    "ErrorMessage19": 235,
    "ErrorMessage2": 230,
    "ErrorMessage20": 163,
    "ErrorMessage21": 82,
    "ErrorMessage22": 240,
    "ErrorMessage23": 168,
    "ErrorMessage24": 275,
    "ErrorMessage25": 158,
    "ErrorMessage26": 153,
    "ErrorMessage27": 173,
    "ErrorMessage28": 178,
    "ErrorMessage29": 183,
    "ErrorMessage3": 213,
    "ErrorMessage30": 188,
    "ErrorMessage31": 193,
    "ErrorMessage32": 198,
    "ErrorMessage33": 203,
    "ErrorMessage34": 208,
    "ErrorMessage35": 280,
    "ErrorMessage37": 112,
    "ErrorMessage38": 117,
    "ErrorMessage4": 286,
    "ErrorMessage6": 77,
    "ErrorMessage7": 92,
    "ErrorMessage8": 97,
    "ErrorMessage9": 102,
    "Fabricante_DataCard1": 209,
    "Fabricante_DataCard2": 251,
    "Fabricante_DataCard3": 93,
    "Fechar": 26,
    "Filtro": 54,
    "Filtro_1": 127,
    "Fontes": 15,
    "Fontes_3": 18,
    "Fontes_4": 22,
    "Form1": 215,
    "Form2": 72,
    "Form5": 148,
    "Gallery2": 134,
    "Gallery2_1": 61,
    "galleryTemplate3": 135,
    "galleryTemplate3_1": 62,
    "Group1": 42,
    "Group10": 143,
    "Group11": 144,
    "Group11_1": 289,
    "Group12": 130,
    "Group2": 17,
    "Group4": 69,
    "Group4_1": 118,
    "Group5": 27,
    "Group7": 57,
    "Group8": 288,
    "Host": 0,
    "Icon1": 292,
    "Icon2": 136,
    "Icon3": 58,
    "Icon3_1": 60,
    "Icon3_2": 131,
    "Icon3_3": 133,
    "Icon4": 146,
    "Icon5": 28,
    "Icon5_1": 36,
    "Icon6": 59,
    "Icon6_1": 132,
    "Icon7": 147,
    "Icon7_2": 71,
    "Icon7_4": 47,
    "Icon7_5": 291,
    "Icon7_6": 120,
    "Image3": 284,
    "Image5": 0,
    "Imagem do material": 124,
    "Imagem do material 2": 51,
    "Label1": 29,
    "Label2_2": 214,
    "Label3": 145,
    "Label3_2": 287,
    "Label3_3": 70,
    "Label3_5": 142,
    "Label3_6": 48,
    "Label3_7": 290,
    "Label3_8": 119,
    "Label4": 21,
    "Label4_1": 16,
    "Localização_DataCard1": 231,
    "Localização_DataCard2": 78,
    "Localização_DataCard4": 169,
    "localizar": 0,
    "Localizar 2": 0,
    "Localizar Button": 32,
    "login": 0,
    "Logo estoque": 31,
    "Logo Estoque": 122,
    "Logo estoque_1": 41,
    "Logo Estoque_1": 49,
    "MABEC_DataCard2": 266,
    "MABEC_DataCard3": 98,
    "MABEC_DataCard4": 174,
    "Material_DataCard1": 179,
    "Material_DataCard2": 216,
    "Material_DataCard3": 73,
    "Modelo Material_DataCard2": 256,
    "Modelo Material_DataCard3": 103,
    "Modelo Material_DataCard4": 184,
    "movimentacao": 0,
    "Movimentacao Button": 33,
    "Movimentacao Button_1": 121,
    "movimentacao2": 0,
    "NextArrow5": 137,
    "NextArrow5_1": 63,
    "Nome (field_2)_DataCard2": 246,
    "Nome_DataCard5": 199,
    "Nota Fiscal_DataCard1": 271,
    "Nota Fiscal_DataCard2": 154,
    "PopUp_acessibilidade": 6,
    "principal": 0,
    "Projeto_DataCard1": 108,
    "Projeto_DataCard2": 159,
    "Projeto_DataCard3": 236,
    "Projeto_DataCard4": 164,
    "Quant._DataCard1": 83,
    "Quant._DataCard2": 241,
    "Quant._DataCard4": 189,
    "Radio1": 55,
    "Radio1_1": 128,
    "Radio1_2": 129,
    "Radio1_3": 56,
    "Referência_DataCard1": 261,
    "Referência_DataCard2": 88,
    "Referência_DataCard4": 194,
    "Separator5_1": 67,
    "Separator5_2": 141,
    "Slider1": 20,
    "StarVisible1": 262,
    "StarVisible10": 222,
    "StarVisible11": 104,
    "StarVisible12": 247,
    "StarVisible13": 217,
    "StarVisible14": 84,
    "StarVisible15": 252,
    "StarVisible16": 267,
    "StarVisible17": 257,
    "StarVisible18": 242,
    "StarVisible19": 232,
    "StarVisible2": 227,
    "StarVisible20": 160,
    "StarVisible21": 79,
    "StarVisible22": 237,
    "StarVisible23": 165,
    "StarVisible24": 272,
    "StarVisible25": 155,
    "StarVisible26": 150,
    "StarVisible27": 170,
    "StarVisible28": 175,
    "StarVisible29": 180,
    "StarVisible3": 210,
    "StarVisible30": 185,
    "StarVisible31": 190,
    "StarVisible32": 195,
    "StarVisible33": 200,
    "StarVisible34": 205,
    "StarVisible35": 277,
    "StarVisible37": 109,
    "StarVisible38": 114,
    "StarVisible4": 282,
    "StarVisible6": 74,
    "StarVisible7": 89,
    "StarVisible8": 94,
    "StarVisible9": 99,
    "Status_DataCard1": 204,
    "Status_DataCard2": 221,
    "Subtitle5": 139,
    "Subtitle5_1": 65,
    "tema": 7,
    "tema claro": 10,
    "tema daltonico": 9,
    "tema escuro": 11,
    "tema_1": 23,
    "Temas": 8,
    "TextInput1": 2,
    "TextInput2": 1,
    "TextInput3": 43,
    "TextInput3_1": 38,
    "TextSearchBox1_1": 126,
    "TextSearchBox1_2": 53,
    "Timer1": 125,
    "Timer1_1": 52,
    "Timer2": 30,
    "Title5": 138,
    "Title5_1": 64,
    "Tooling Logo": 37,
    "Tooling Logo_1": 4,
    "Tooling Logo_2": 68,
    "Tooling Logo_4": 46,
    "UploadedImage1": 40
  },
  "ResourcesJsonIndices": {
    "Image-1": 6,
    "Image-186203": 13,
    "Image-197376": 12,
    "Image-197573": 14,
    "Image-2": 7,
    "Image-2_1": 11,
    "Image-Design sem nome": 8,
    "Image-Design sem nome (1)": 9,
    "Image-Design sem nome (2)": 10,
    "Image-Imagem não encontrada": 5,
    "Image-Logo Tooling - vetor": 1,
    "Image-MicrosoftTeams-image (2)": 2,
    "Image-MicrosoftTeams-image (5)": 3,
    "Image-MicrosoftTeams-image (6)": 4,
    "Image-SampleImage": 0,
    "Pdf-SamplePdf": 15
  },
  "RuleScreenIdWithoutScreen": {},
  "TemplateVersions": {},
  "VolatileProperties": {
    "AnalysisLoadTime": 1.9183278,
    "ControlCount": {
      "addMedia": 2,
      "attachments": 2,
      "button": 16,
      "combobox": 9,
      "datepicker": 2,
      "form": 3,
      "gallery": 2,
      "galleryTemplate": 2,
      "group": 13,
      "groupContainer": 5,
      "icon": 19,
      "image": 18,
      "label": 125,
      "radio": 4,
      "rectangle": 3,
      "screen": 7,
      "slider": 1,
      "text": 28,
      "timer": 3,
      "typedDataCard": 36
    },
    "DeserializationLoadTime": 3.341609
  },
  "WasLocalDatabaseReferencesEmpty": true
}